{"geocoding": {"version": "0.2", "attribution": "https://openrouteservice.org/terms-of-service/#attribution-geocode", "query": {"text": "braunschw", "parser": "pelias", "parsed_text": {"subject": "braunschw"}, "size": 5, "layers": ["venue", "street", "country", "macroregion", "region", "county", "localadmin", "locality", "borough", "neighbourhood", "continent", "empire", "dependency", "macrocounty", "macrohood", "microhood", "disputed", "postalcode", "ocean", "marinearea"], "private": false, "boundary.country": ["DEU", "AUT", "CHE", "DNK", "NOR", "SWE", "NLD", "BEL", "FRA", "ITA"], "lang": {"name": "German", "iso6391": "de", "iso6393": "deu", "via": "querystring", "defaulted": false}, "querySize": 20}, "warnings": ["performance optimization: excluding 'address' layer"], "engine": {"name": "Pelias", "author": "Mapzen", "version": "1.0"}, "timestamp": 1762506585363}, "type": "FeatureCollection", "features": [{"type": "Feature", "geometry": {"type": "Point", "coordinates": [10.53528, 52.28528]}, "properties": {"id": "3221011", "gid": "geonames:locality:3221011", "layer": "locality", "source": "geonames", "source_id": "3221011", "name": "Kreisfreie Stadt Braunschweig", "accuracy": "centroid", "country": "Deutschland", "country_gid": "whosonfirst:country:85633111", "country_a": "DEU", "region": "Niedersachsen", "region_gid": "whosonfirst:region:85682555", "region_a": "NI", "county": "Wolfenb\u00fcttel", "county_gid": "whosonfirst:county:102063881", "county_a": "WB", "localadmin": "Cremlingen", "localadmin_gid": "whosonfirst:localadmin:1377686093", "locality": "Kreisfreie Stadt Braunschweig", "locality_gid": "geonames:locality:3221011", "continent": "Europa", "continent_gid": "whosonfirst:continent:102191581", "label": "Kreisfreie Stadt Braunschweig, NI, Deutschland", "addendum": {"geonames": {"feature_code": "ADM3"}}}}, {"type": "Feature", "geometry": {"type": "Point", "coordinates": [10.625469, 52.272012]}, "properties": {"id": "101909589", "gid": "whosonfirst:locality:101909589", "layer": "locality", "source": "whosonfirst", "source_id": "101909589", "name": "Braunschweig", "accuracy": "centroid", "country": "Deutschland", "country_gid": "whosonfirst:country:85633111", "country_a": "DEU", "region": "Niedersachsen", "region_gid": "whosonfirst:region:85682555", "region_a": "NI", "county": "Wolfenb\u00fcttel", "county_gid": "whosonfirst:county:102063881", "localadmin": "Cremlingen", "localadmin_gid": "whosonfirst:localadmin:1377686093", "locality": "Braunschweig", "locality_gid": "whosonfirst:locality:101909589", "continent": "Europa", "continent_gid": "whosonfirst:continent:102191581", "label": "Braunschweig, NI, Deutschland", "addendum": {"concordances": {"gn:id": 2945024, "gp:id": 637084, "qs_pg:id": 1056248, "wd:id": "Q2773", "wk:page": "Braunschweig", "qs:id": 633573}}}, "bbox": [10.4124136891, 52.1865105584, 10.642989265, 52.3574693038]}, {"type": "Feature", "geometry": {"type": "Point", "coordinates": [10.52673, 52.26594]}, "properties": {"id": "2945024", "gid": "geonames:locality:2945024", "layer": "locality", "source": "geonames", "source_id": "2945024", "name": "Braunschweig", "accuracy": "centroid", "country": "Deutschland", "country_gid": "whosonfirst:country:85633111", "country_a": "DEU", "region": "Niedersachsen", "region_gid": "whosonfirst:region:85682555", "region_a": "NI", "county": "Wolfenb\u00fcttel", "county_gid": "whosonfirst:county:102063881", "county_a": "WB", "localadmin": "Cremlingen", "localadmin_gid": "whosonfirst:localadmin:1377686093", "locality": "Braunschweig", "locality_gid": "geonames:locality:2945024", "continent": "Europa", "continent_gid": "whosonfirst:continent:102191581", "label": "Braunschweig, NI, Deutschland", "addendum": {"geonames": {"feature_code": "PPLA3"}}}}, {"type": "Feature", "geometry": {"type": "Point", "coordinates": [10.526247, 52.264833]}, "properties": {"id": "102063903", "gid": "whosonfirst:county:102063903", "layer": "county", "source": "whosonfirst", "source_id": "102063903", "name": "Landkreis Braunschweig", "accuracy": "centroid", "country": "Deutschland", "country_gid": "whosonfirst:country:85633111", "country_a": "DEU", "region": "Niedersachsen", "region_gid": "whosonfirst:region:85682555", "region_a": "NI", "county": "Landkreis Braunschweig", "county_gid": "whosonfirst:county:102063903", "continent": "Europa", "continent_gid": "whosonfirst:continent:102191581", "label": "Landkreis Braunschweig, NI, Deutschland", "addendum": {"concordances": {"hasc:id": "DE.NI.BA", "wd:id": "Q1803098"}}}, "bbox": [10.412414, 52.186511, 10.642989, 52.357469]}, {"type": "Feature", "geometry": {"type": "Point", "coordinates": [11.24384, 51.590303]}, "properties": {"id": "101909219", "gid": "whosonfirst:locality:101909219", "layer": "locality", "source": "whosonfirst", "source_id": "101909219", "name": "Braunschwende", "accuracy": "centroid", "country": "Deutschland", "country_gid": "whosonfirst:country:85633111", "country_a": "DEU", "region": "Sachsen-Anhalt", "region_gid": "whosonfirst:region:85682519", "region_a": "ST", "county": "Landkreis Mansfeld-S\u00fcdharz", "county_gid": "whosonfirst:county:102063819", "localadmin": "Mansfeld", "localadmin_gid": "whosonfirst:localadmin:1377688765", "locality": "Braunschwende", "locality_gid": "whosonfirst:locality:101909219", "continent": "Europa", "continent_gid": "whosonfirst:continent:102191581", "label": "Braunschwende, ST, Deutschland", "addendum": {"concordances": {"gn:id": 2945022, "gp:id": 640832, "qs_pg:id": 347192, "wd:id": "Q681597", "wk:page": "Braunschwende"}}}, "bbox": [11.2365573924, 51.5853904162, 11.2540670323, 51.5934476522]}], "bbox": [10.4124136891, 51.5853904162, 11.2540670323, 52.3574693038]}